pymotif/__init__.py
pymotif/_frontend.py
pymotif/_version.py
pymotif/constants.py
pymotif/example.py
pymotif/motif.py
pymotif/labextension/package.json
pymotif/labextension/static/123.3411b80d8df4f69e811d.js
pymotif/labextension/static/123.bb60d90e717ef3cd409e.js
pymotif/labextension/static/24.350e94b7edbc314c9060.js
pymotif/labextension/static/24.b2600497b020256987ad.js
pymotif/labextension/static/25.6beb8ab1951375dccfe3.js
pymotif/labextension/static/30.3fe83ee266277dc6163e.js
pymotif/labextension/static/30.db4189f346ea33876c8e.js
pymotif/labextension/static/355.509f89089b13ed6f9cdd.js
pymotif/labextension/static/355.727327834367f8db672a.js
pymotif/labextension/static/419.18a52d5fea5c72872fc6.js
pymotif/labextension/static/419.f7ef48e3876ebb5471f2.js
pymotif/labextension/static/480.0e4705fcc36a9f970eab.js
pymotif/labextension/static/480.b9ba3434ae80db225193.js
pymotif/labextension/static/534.1f766f1523925f7b0a8c.js
pymotif/labextension/static/534.5a96c333af354f43d321.js
pymotif/labextension/static/565.84e441327c24143dc738.js
pymotif/labextension/static/565.84e441327c24143dc738.js.LICENSE.txt
pymotif/labextension/static/565.c720df2eed12c5833f4c.js
pymotif/labextension/static/565.c720df2eed12c5833f4c.js.LICENSE.txt
pymotif/labextension/static/568.057fad915335f1e1fe88.js
pymotif/labextension/static/568.057fad915335f1e1fe88.js.LICENSE.txt
pymotif/labextension/static/568.1520a9946baff503a701.js
pymotif/labextension/static/568.b0f812c66cd76c76f570.js
pymotif/labextension/static/597.c021a5976810168f724f.js
pymotif/labextension/static/597.daf0789ea312688bdde4.js
pymotif/labextension/static/606.07610e057b0e528f6d90.js
pymotif/labextension/static/606.07610e057b0e528f6d90.js.LICENSE.txt
pymotif/labextension/static/606.425d2a4e5445a1ebdb9f.js
pymotif/labextension/static/606.425d2a4e5445a1ebdb9f.js.LICENSE.txt
pymotif/labextension/static/606.5093f90a9c1e4e029268.js
pymotif/labextension/static/606.5093f90a9c1e4e029268.js.LICENSE.txt
pymotif-0.0.6.dist-info/LICENSE.txt
pymotif-0.0.6.dist-info/METADATA
pymotif-0.0.6.dist-info/WHEEL
pymotif-0.0.6.dist-info/top_level.txt
pymotif-0.0.6.dist-info/RECORD
